django_mri/__init__.py
django_mri/admin.py
django_mri/apps.py
django_mri/urls.py
django_mri/analysis/__init__.py
django_mri/analysis/analysis_definitions.py
django_mri/analysis/interfaces.py
django_mri/data_import/__init__.py
django_mri/data_import/import_scan.py
django_mri/data_import/local_import.py
django_mri/filters/__init__.py
django_mri/filters/scan_filter.py
django_mri/filters/sequence_type_filter.py
django_mri/interfaces/__init__.py
django_mri/interfaces/dcm2niix.py
django_mri/migrations/__init__.py
django_mri/models/__init__.py
django_mri/models/common_sequences.py
django_mri/models/fields.py
django_mri/models/nifti.py
django_mri/models/scan.py
django_mri/models/sequence_type.py
django_mri/models/choices/__init__.py
django_mri/models/choices/scanning_sequence.py
django_mri/models/choices/sequence_variant.py
django_mri/serializers/__init__.py
django_mri/serializers/nifti.py
django_mri/serializers/scan.py
django_mri/serializers/sequence_type.py
django_mri/utils/__init__.py
django_mri/utils/utils.py
django_mri/views/__init__.py
django_mri/views/defaults.py
django_mri/views/nifti.py
django_mri/views/pagination.py
django_mri/views/scan.py
django_mri/views/sequence_type.py
tests/__init__.py
tests/factories.py
tests/fixtures.py
tests/test_settings.py
tests/data_import/__init__.py
tests/data_import/test_local_import.py
tests/models/__init__.py
tests/models/test_nifti.py
tests/models/test_scan.py
tests/models/test_sequence_type.py
django_mri-0.0.4.dist-info/LICENSE
django_mri-0.0.4.dist-info/METADATA
django_mri-0.0.4.dist-info/WHEEL
django_mri-0.0.4.dist-info/top_level.txt
django_mri-0.0.4.dist-info/RECORD
